LICENSE
bigearthnet_common/BigEarthNet-S1-Example.tar.bz2
bigearthnet_common/BigEarthNet-S2-Example.tar.bz2
bigearthnet_common/__init__.py
bigearthnet_common/base.py
bigearthnet_common/constants.py
bigearthnet_common/example_data.py
bigearthnet_common/patches_with_cloud_and_shadow.csv.bz2
bigearthnet_common/patches_with_no_19_class_targets.csv.bz2
bigearthnet_common/patches_with_seasonal_snow.csv.bz2
bigearthnet_common/s1_s2_name_country_season.csv.bz2
bigearthnet_common/sets.py
bigearthnet_common/test.csv.bz2
bigearthnet_common/train.csv.bz2
bigearthnet_common/val.csv.bz2
bigearthnet_common-2.8.0.dist-info/entry_points.txt
bigearthnet_common-2.8.0.dist-info/WHEEL
bigearthnet_common-2.8.0.dist-info/METADATA
bigearthnet_common-2.8.0.dist-info/license_files/LICENSE
bigearthnet_common-2.8.0.dist-info/RECORD
