Metadata-Version: 2.1
Name: bigearthnet-common
Version: 2.8.0
Summary: A collection of common tools to interact with the BigEarthNet dataset.
License: Apache Software License 2.0
Keywords: ben,bigearthnet,script,tools
Author-email: Kai Norman Clasen <k.clasen@protonmail.com>
Requires-Python: >=3.8
Requires-Dist: appdirs>=1.4
Requires-Dist: fastcore>=1.3
Requires-Dist: natsort>=8
Requires-Dist: pydantic>=1.8
Requires-Dist: python-dateutil>=2
Requires-Dist: typer[all]>=0.6
Project-URL: documentation, https://kai-tub.github.io/bigearthnet_common
Project-URL: homepage, https://github.com/kai-tub/bigearthnet_common/
Project-URL: repository, https://github.com/kai-tub/bigearthnet_common/
